<?xml version="1.0" encoding="UTF-8"?>
<beans:beans 
	xmlns ="http://www.springframework.org/schema/security"
    xmlns:beans="http://www.springframework.org/schema/beans"
	xmlns:xsi="http://www.w3.org/2001/XMLSchema-instance"
	xsi:schemaLocation="
	    http://www.springframework.org/schema/security 
	    http://www.springframework.org/schema/security/spring-security-5.4.xsd
		http://www.springframework.org/schema/beans 
		http://www.springframework.org/schema/beans/spring-beans-4.3.xsd">
		
	<!-- http 설정 -->	               
	<http auto-config="true" use-expressions="true">
	   <intercept-url pattern="/admin/**" access="hasRole('ROLE_ADMIN')" />
	   <intercept-url pattern="/member/**" access="hasAnyRole('ROLE_ADMIN', 'ROLE_USer')" />
	   <form-login login-page="/login" default-target-url="/index" authentication-failure-url="/index?error=error"/>
	   <logout logout-success-url="/index?logout=logout"/>
	   <csrf/>
	</http>
	
	<!-- Authentication 메니저 설정 -->	    
	<user-service>
		<user name="user" password="password" authorities="ROLE_USER" />
	</user-service> 
	
	<beans:bean id="passwordEncoder" class="org.springframework.security.crypto.bcrypt.BCryptPasswordEncoder"/>          
</beans:beans>
